MANIFEST.in
README.rst
UNLICENSE
setup.py
black_magic/__init__.py
black_magic/common.py
black_magic/compat.py
black_magic/decorator.py
black_magic.egg-info/PKG-INFO
black_magic.egg-info/SOURCES.txt
black_magic.egg-info/dependency_links.txt
black_magic.egg-info/requires.txt
black_magic.egg-info/top_level.txt
test/test_decorator.py
test/test_partial.py