Metadata-Version: 1.1
Name: black-magic
Version: 0.0.12
Summary: Decorator utility that operates on black magic
Home-page: https://github.com/coldfix/black-magic
Author: Thomas Gläßle
Author-email: t_glaessle@gmx.de
License: Unlicense
Platform: UNKNOWN
Classifier: Development Status :: 3 - Alpha
Classifier: Intended Audience :: Developers
Classifier: Operating System :: OS Independent
Classifier: Programming Language :: Python
Classifier: Programming Language :: Python :: 2.6
Classifier: Programming Language :: Python :: 2.7
Classifier: Programming Language :: Python :: 3.2
Classifier: Programming Language :: Python :: 3.3
Classifier: Programming Language :: Python :: 3.4
Classifier: Programming Language :: Python :: 3.5
Classifier: Topic :: Software Development
Classifier: License :: Public Domain
